{
  "generatedAt": "2026-03-07T21:20:14.587Z",
  "capabilities": {
    "managedBrowser": true,
    "attachedChrome": true,
    "attachedChromePaired": true,
    "nodeHostConfigured": true,
    "nodeHostReady": true,
    "gatewayTokenConfigured": true,
    "remoteGatewayConfigured": true,
    "remoteGatewayBaseUrl": "http://127.0.0.1:4201",
    "remoteGatewayMode": "ssh-tunnel",
    "steel": false,
    "steelMode": "none",
    "steelReady": false,
    "steelBaseUrl": "",
    "steelAuthConfigured": false,
    "steelApiConfigured": false,
    "steelCredentialsSupported": false,
    "steelProfilesSupported": false,
    "steelSessionPersistenceSupported": false,
    "steelLiveDebugSupported": false,
    "steelAuthStateReady": false
  },
  "profiles": [
    {
      "id": "openclaw_research",
      "lane": "openclaw-managed",
      "namespace": "openclaw_research",
      "purpose": "Default managed-browser lane for research and low-trust site work.",
      "riskBoundary": "public-web",
      "persistent": false
    },
    {
      "id": "chrome_company",
      "lane": "attached-chrome",
      "namespace": "chrome_company",
      "purpose": "Attached local Chrome for company-authenticated sessions and operator-visible debugging.",
      "riskBoundary": "company-auth",
      "persistent": true
    },
    {
      "id": "clean_research",
      "lane": "steel",
      "namespace": "clean_research",
      "purpose": "Parallel Steel research sessions with isolated, low-trust state.",
      "riskBoundary": "public-web",
      "persistent": true
    },
    {
      "id": "company_signup_identity",
      "lane": "steel",
      "namespace": "company_signup_identity",
      "purpose": "Steel namespace for new company signups and verification flows.",
      "riskBoundary": "company-auth",
      "persistent": true
    },
    {
      "id": "gmail_primary",
      "lane": "steel",
      "namespace": "gmail_primary",
      "purpose": "Steel namespace for the company Gmail inbox and email-confirmation flows.",
      "riskBoundary": "root-identity",
      "persistent": true
    },
    {
      "id": "wise_primary",
      "lane": "steel",
      "namespace": "wise_primary",
      "purpose": "Steel namespace for Wise browser fallback tasks when token APIs are insufficient.",
      "riskBoundary": "treasury",
      "persistent": true
    },
    {
      "id": "hetzner_primary",
      "lane": "steel",
      "namespace": "hetzner_primary",
      "purpose": "Steel namespace for Hetzner console and infrastructure tasks.",
      "riskBoundary": "infrastructure",
      "persistent": true
    },
    {
      "id": "marketplace_generic",
      "lane": "steel",
      "namespace": "marketplace_generic",
      "purpose": "Steel namespace for scalable marketplace listing operations.",
      "riskBoundary": "company-auth",
      "persistent": true
    }
  ],
  "sampleRoutes": [
    {
      "taskId": "market-research",
      "status": "ready",
      "lane": "openclaw-managed",
      "profileId": "openclaw_research",
      "headless": true,
      "reasons": [
        "OpenClaw managed browser is the default typed lane for public or low-trust work."
      ]
    },
    {
      "taskId": "wise-reconcile",
      "status": "ready",
      "lane": "attached-chrome",
      "profileId": "chrome_company",
      "headless": false,
      "reasons": [
        "High-trust work prefers attached Chrome when the paired relay and node host are both ready."
      ]
    },
    {
      "taskId": "signup-run",
      "status": "blocked",
      "lane": "blocked",
      "profileId": null,
      "headless": false,
      "blockerReason": "company-auth-lane-unavailable",
      "reasons": [
        "Company-auth work that needs persistent state will not silently fall back to the generic managed browser."
      ]
    }
  ],
  "activeSessions": 1
}
